NiukeBiMianshiBibeiSuanfaXuexiBijiZhiShujuchuliJingjiangFix1/README.md
NiukeBiMianshiBibeiSuanfaXuexiBijiZhiShujuchuliJingjiangFix1/__init__.py
NiukeBiMianshiBibeiSuanfaXuexiBijiZhiShujuchuliJingjiangFix1/__main__.py
NiukeBiMianshiBibeiSuanfaXuexiBijiZhiShujuchuliJingjiangFix1/file.epub
NiukeBiMianshiBibeiSuanfaXuexiBijiZhiShujuchuliJingjiangFix1/index.html
NiukeBiMianshiBibeiSuanfaXuexiBijiZhiShujuchuliJingjiangFix1/css/__init__.py
NiukeBiMianshiBibeiSuanfaXuexiBijiZhiShujuchuliJingjiangFix1/css/annotations.css
NiukeBiMianshiBibeiSuanfaXuexiBijiZhiShujuchuliJingjiangFix1/css/main.css
NiukeBiMianshiBibeiSuanfaXuexiBijiZhiShujuchuliJingjiangFix1/css/normalize.css
NiukeBiMianshiBibeiSuanfaXuexiBijiZhiShujuchuliJingjiangFix1/css/popup.css
NiukeBiMianshiBibeiSuanfaXuexiBijiZhiShujuchuliJingjiangFix1/font/__init__.py
NiukeBiMianshiBibeiSuanfaXuexiBijiZhiShujuchuliJingjiangFix1/font/fontello.eot
NiukeBiMianshiBibeiSuanfaXuexiBijiZhiShujuchuliJingjiangFix1/font/fontello.svg
NiukeBiMianshiBibeiSuanfaXuexiBijiZhiShujuchuliJingjiangFix1/font/fontello.ttf
NiukeBiMianshiBibeiSuanfaXuexiBijiZhiShujuchuliJingjiangFix1/font/fontello.woff
NiukeBiMianshiBibeiSuanfaXuexiBijiZhiShujuchuliJingjiangFix1/img/__init__.py
NiukeBiMianshiBibeiSuanfaXuexiBijiZhiShujuchuliJingjiangFix1/img/annotator-glyph-sprite.png
NiukeBiMianshiBibeiSuanfaXuexiBijiZhiShujuchuliJingjiangFix1/img/annotator-icon-sprite.png
NiukeBiMianshiBibeiSuanfaXuexiBijiZhiShujuchuliJingjiangFix1/img/apple-touch-icon.png
NiukeBiMianshiBibeiSuanfaXuexiBijiZhiShujuchuliJingjiangFix1/img/cancelfullscreen.png
NiukeBiMianshiBibeiSuanfaXuexiBijiZhiShujuchuliJingjiangFix1/img/close.png
NiukeBiMianshiBibeiSuanfaXuexiBijiZhiShujuchuliJingjiangFix1/img/fullscreen.png
NiukeBiMianshiBibeiSuanfaXuexiBijiZhiShujuchuliJingjiangFix1/img/loader.gif
NiukeBiMianshiBibeiSuanfaXuexiBijiZhiShujuchuliJingjiangFix1/img/menu-icon.png
NiukeBiMianshiBibeiSuanfaXuexiBijiZhiShujuchuliJingjiangFix1/img/save.png
niuke_bi_mianshi_bibei_suanfa_xuexi_biji_zhi_shujuchuli_jingjiang_fix1-2025.3.25.0.dist-info/METADATA
niuke_bi_mianshi_bibei_suanfa_xuexi_biji_zhi_shujuchuli_jingjiang_fix1-2025.3.25.0.dist-info/WHEEL
niuke_bi_mianshi_bibei_suanfa_xuexi_biji_zhi_shujuchuli_jingjiang_fix1-2025.3.25.0.dist-info/entry_points.txt
niuke_bi_mianshi_bibei_suanfa_xuexi_biji_zhi_shujuchuli_jingjiang_fix1-2025.3.25.0.dist-info/top_level.txt
niuke_bi_mianshi_bibei_suanfa_xuexi_biji_zhi_shujuchuli_jingjiang_fix1-2025.3.25.0.dist-info/RECORD
